asciidag/__init__.py
asciidag/color.py
asciidag/graph.py
asciidag/node.py
asciidag/sequence.py
asciidag-0.2.0.dist-info/AUTHORS.rst
asciidag-0.2.0.dist-info/LICENSE
asciidag-0.2.0.dist-info/METADATA
asciidag-0.2.0.dist-info/WHEEL
asciidag-0.2.0.dist-info/top_level.txt
asciidag-0.2.0.dist-info/RECORD
